<?xml version="1.0" encoding="UTF-8"?>
<LanguageData>
  
  <!-- EN: ambrosia addiction -->
  <AmbrosiaAddiction.label>addicció a l’ambrosia</AmbrosiaAddiction.label>
  <!-- EN: A chemical addiction to ambrosia. Long-term presence of ambrosia has caused neurological adaptations at the cellular level, so the brain can no longer function properly without the drug.\n\nWithout regular doses of ambrosia, withdrawal symptoms will begin. However, extended abstinence will force the brain to adapt back to its normal state, resolving the addiction. -->
  <AmbrosiaAddiction.description>Addicció química a l’ambrosia. La presència prolongada a la sang d’aquesta substància ha provocat adaptacions neuronals a nivell cel·lular. El cervell ja no pot funcionar adequadament sense la droga.\n\nSi no es prenen dosis regulars, apareixeran símptomes del síndrome d’abstinència. No obstant, si es continua sense prendre’n, el cervell recuperarà el seu estat normal i es recuperarà de l’addicció.</AmbrosiaAddiction.description>
  <!-- EN: withdrawal -->
  <AmbrosiaAddiction.stages.withdrawal.label>abstinència</AmbrosiaAddiction.stages.withdrawal.label>
  
  <!-- EN: ambrosia warmth -->
  <AmbrosiaHigh.label>benestar d’ambrosia</AmbrosiaHigh.label>
  <!-- EN: Ambrosia chemicals in the bloodstream. It lifts the mood. -->
  <AmbrosiaHigh.description>Hi ha components químics de l’ambrosia a la sang. Millora l’estat d’ànim.</AmbrosiaHigh.description>
  
  <!-- EN: ambrosia tolerance -->
  <AmbrosiaTolerance.label>tolerància a l’ambrosia</AmbrosiaTolerance.label>
  <!-- EN: A built-up tolerance to ambrosia. The more severe this tolerance is, the more ambrosia it takes to get the same effect. -->
  <AmbrosiaTolerance.description>Tolerància adquirida a l’ambrosia. Com més severa sigui, més ambrosia caldrà consumir per aconseguir el mateix efecte.</AmbrosiaTolerance.description>
  <!-- EN: small -->
  <AmbrosiaTolerance.stages.small.label>mínima</AmbrosiaTolerance.stages.small.label>
  <!-- EN: large -->
  <AmbrosiaTolerance.stages.large.label>molta</AmbrosiaTolerance.stages.large.label>
  <!-- EN: massive -->
  <AmbrosiaTolerance.stages.massive.label>enorme</AmbrosiaTolerance.stages.massive.label>
  
</LanguageData>