<?xml version="1.0" encoding="UTF-8"?>
<LanguageData>
  
  <!-- EN: The child of an illicit affair, [PAWN_nameDef] was bought up by ascetics in a medieval convent. [PAWN_pronoun] learned the value of hard work and submission, but was taught that technology is heretical and violence immortal. -->
  <ConventChild16.description>{PAWN_gender ? Nascut : Nascuda} d’una aventura fora del matrimoni, a [PAWN_nameDef] [PAWN_pronoun] van criar els ascetes d’un convent medieval. Va aprendre el valor de l’esforç pel treball i l’obediència, però també li van inculcar que la tecnologia és una heretgia i que la violència era immoral.</ConventChild16.description>
  <!-- EN: convent child -->
  <ConventChild16.title>nen criat en un convent</ConventChild16.title>
  <ConventChild16.titleFemale>nena criada en un convent</ConventChild16.titleFemale>
  <!-- EN: illicit -->
  <ConventChild16.titleShort>nen</ConventChild16.titleShort>
  <ConventChild16.titleShortFemale>nena</ConventChild16.titleShortFemale>
  
  <!-- EN: [PAWN_nameDef] was a minor noble in an old kingdom on a medieval world. [PAWN_pronoun] grew up in a manor made of handcut stone, served by servants of the lower classes.\n\nSuch a life teaches no technical skills and instils a lifelong aversion to manual labor - but [PAWN_nameDef] learned early the ways of social manipulation. -->
  <MedievalLordling19.description>[PAWN_nameDef] pertanyia a la noblesa menor en un regne d’un món medieval. Es va criar en una mansió de pedra tallada a mà, {PAWN_gender ? envoltat : envoltada} de criats servils.\n\nAquest tipus de vida no ensenya habilitats tècniques i indueix aversió a les feines manuals – però va aprendre ben aviat els mètodes de la manipulació social.</MedievalLordling19.description>
  <!-- EN: medieval lordling -->
  <MedievalLordling19.title>hidalgo medieval</MedievalLordling19.title>
  <!-- EN: medieval lady -->
  <MedievalLordling19.titleFemale>dama medieval</MedievalLordling19.titleFemale>
  <!-- EN: lordling -->
  <MedievalLordling19.titleShort>hidalgo</MedievalLordling19.titleShort>
  <!-- EN: lady -->
  <MedievalLordling19.titleShortFemale>dama</MedievalLordling19.titleShortFemale>
  
  <!-- EN: [PAWN_nameDef] grew up pulling carts and digging holes on a medieval world. Simple manual labor is [PAWN_possessive] oldest companion - along with the master's lash.\n\n[PAWN_pronoun] didn't learn to read until age nine. -->
  <MedievalSlave49.description>[PAWN_nameDef] va créixer estirant carros i cavant forats en un món medieval. El treball manual i senzill és el seu company més antic, juntament amb el fuet de l’amo.\n\nNo va aprendre a llegir fins als 9 anys.</MedievalSlave49.description>
  <!-- EN: medieval slave -->
  <MedievalSlave49.title>esclau medieval</MedievalSlave49.title>
  <MedievalSlave49.titleFemale>esclava medieval</MedievalSlave49.titleFemale>
  <!-- EN: slave -->
  <MedievalSlave49.titleShort>esclau</MedievalSlave49.titleShort>
  <MedievalSlave49.titleShortFemale>esclava</MedievalSlave49.titleShortFemale>
  
</LanguageData>