<?xml version="1.0" encoding="UTF-8"?>
<LanguageData>
  <!-- EN: Multiplier for enslaved (low motivation) -->
  <StatsReport_Slave>Multiplicador pels esclaus (motivació baixa)</StatsReport_Slave>
  <!-- EN: Terror offset -->
  <StatsReport_Terror>Modificador de terror</StatsReport_Terror>
  <!-- EN: Faction leader bonus -->
  <StatsReport_LeaderOffset>Bonificació per líder de facció</StatsReport_LeaderOffset>
  <!-- EN: Contains corpse -->
  <StatsReport_OccupiedCorpseCasket>Conté un cadàver</StatsReport_OccupiedCorpseCasket>

  <!-- EN: Conversion power bonus on map -->
  <StatsReport_InstalledRelicConvertPowerFactor>Bonificació del poder de conversió al mapa</StatsReport_InstalledRelicConvertPowerFactor>
  <!-- EN: Mood bonus for rituals in room -->
  <StatsReport_RelicAtRitualMoodBonus>Bonificació d’estat d’ànim pels rituals a la cambra</StatsReport_RelicAtRitualMoodBonus>

  <!-- EN: Relic of -->
  <Stat_Thing_RelicOf_Name>Relíquia de</Stat_Thing_RelicOf_Name>
  <!-- EN: The ideology this relic belongs to. -->
  <Stat_Thing_RelicOf_Desc>La ideoligió a la que pertany la relíquia.</Stat_Thing_RelicOf_Desc>
  <!-- EN: Relic status -->
  <Stat_Thing_RelicStatus>Estat de la relíquia</Stat_Thing_RelicStatus>
  <!-- EN: A widely sought-after item of religious or ideological significance. -->
  <Stat_Thing_RelicStatus_Desc>Un element molt buscat d’importància religiosa o ideològica.</Stat_Thing_RelicStatus_Desc>

  <!-- EN: Related to -->
  <Stat_Thing_RelatedToIdeos_Name>Relacionat amb</Stat_Thing_RelatedToIdeos_Name>
  <!-- EN: The ideoligions this thing belongs to. -->
  <Stat_Thing_RelatedToIdeos_Desc>Les ideoligions amb què està relacionat.</Stat_Thing_RelatedToIdeos_Desc>

  <!-- EN: Holding relic -->
  <StatsReports_HasRelic>Possessió de relíquia</StatsReports_HasRelic>

  <!-- EN: Blind bonus -->
  <StatsReport_BlindPsychicSensitivityOffset>Bonificació per ceguera</StatsReport_BlindPsychicSensitivityOffset>
  <!-- EN: Sight bonus -->
  <StatsReport_SightPsychicSensitivityOffset>Bonificació per vista</StatsReport_SightPsychicSensitivityOffset>

  <!-- EN: Dominating style -->
  <Stat_Thing_StyleDominanceCategory>Estil dominant</Stat_Thing_StyleDominanceCategory>
  <!-- EN: The style presented by this object. This style may be associated with some ideoligions. Different people respond differently to certain styles, according to their ideoligious beliefs. -->
  <Stat_Thing_StyleDominanceCategoryDesc>L’estil d’aquest objecte. L’estil pot estar associat amb algunes ideoligions. Cada persona respon de manera diferent a diferents estils, d’acord amb les seves creences ideoligioses.</Stat_Thing_StyleDominanceCategoryDesc>
  <!-- EN: Satisfies ideoligions -->
  <Stat_Thing_IdeosSatisfied>Satisfà les ideoligions</Stat_Thing_IdeosSatisfied>

  <!-- EN: Darkness shooting accuracy -->
  <Stat_Pawn_DarknessCombatShooting_Name>Precisió per disparar a la foscor</Stat_Pawn_DarknessCombatShooting_Name>
  <!-- EN: An offset applied to the chance to hit a target based on the target's light level. -->
  <Stat_Pawn_DarknessCombatShooting_Desc>Un modificador que s’aplica a la probabilitat d’encertar l’objectiu que depèn del nivell d’il·luminació de l’objectiu.</Stat_Pawn_DarknessCombatShooting_Desc>
  <!-- EN: Darkness melee dodge chance -->
  <Stat_Pawn_DarknessMeleeDodgeChance_Name>Probabilitat d’esquivar un atac cos a cos a la foscor</Stat_Pawn_DarknessMeleeDodgeChance_Name>
  <!-- EN: An offset applied to the melee dodge chance based on the target's light level. -->
  <Stat_Pawn_DarknessMeleeDodgeChance_Desc>Modificador que s’aplica a la probabilitat d’esquivar un atac cos a cos en funció del nivell d’il·luminació de l’objectiu.</Stat_Pawn_DarknessMeleeDodgeChance_Desc>
  <!-- EN: Darkness melee hit chance -->
  <Stat_Pawn_DarknessMeleeHitChance_Name>Probabilitat d’impacte de l’atac cos a cos a la foscor</Stat_Pawn_DarknessMeleeHitChance_Name>
  <!-- EN: An offset applied to the melee hit chance based on the target's light level. -->
  <Stat_Pawn_DarknessMeleeHitChance_Desc>Un modificador que s’aplica a la probabilitat d’impacte dels atacs cos a cos en funció del nivell d’il·luminació de l’objectiu.</Stat_Pawn_DarknessMeleeHitChance_Desc>
  <!-- EN: The following offsets can be applied -->
  <Stat_PawnDarkness_FollowingOffset>Es poden aplicar els modificadors següents</Stat_PawnDarkness_FollowingOffset>

  <!-- EN: Biosculpting speed -->
  <StatsReport_BiosculptingSpeedFactor>Velocitat de la bioescultura</StatsReport_BiosculptingSpeedFactor>

  <!-- EN: The amount of progress that has been made towards hacking this object. -->
  <Stat_Thing_HackingProgress>Quantitat de progrés que s’ha fet per a hackejar aquest objecte.</Stat_Thing_HackingProgress>

  </LanguageData>