<?xml version="1.0" encoding="UTF-8"?>
<LanguageData>
  
  <!-- EN: high life -->
  <HighLife.stages.high_life-0.label>col·locarisme</HighLife.stages.high_life-0.label>
  <!-- EN: The right path goes through altered consciousness, and I am walking it. -->
  <HighLife.stages.high_life-0.description>El camí correcte és el que ens porta per una consciència alterada i jo segueixo el camí.</HighLife.stages.high_life-0.description>
  <!-- EN: high life -->
  <HighLife.stages.high_life-1.label>col·locarisme</HighLife.stages.high_life-1.label>
  <!-- EN: high life missing -->
  <HighLife.stages.high_life_missing-0.label>no vaig col·locat</HighLife.stages.high_life_missing-0.label>
  <!-- EN: I should be altering my consciousness. It's not right to be sober so long. -->
  <HighLife.stages.high_life_missing-0.description>Hauria de tenir la consciència alterada. No és correcte anar per la vida sobri tant de temps.</HighLife.stages.high_life_missing-0.description>
  <!-- EN: high life missing -->
  <HighLife.stages.high_life_missing-1.label>no vaig col·locat</HighLife.stages.high_life_missing-1.label>
  <!-- EN: I should be altering my consciousness. It's not right to be sober so long. -->
  <HighLife.stages.high_life_missing-1.description>Hauria de tenir la consciència alterada. No és correcte anar per la vida sobri tant de temps.</HighLife.stages.high_life_missing-1.description>
  
</LanguageData>