<?xml version="1.0" encoding="utf-8"?>
<LanguageData>

  <Heatstroke.label>cop de calor</Heatstroke.label>
  <Heatstroke.stages.0.label>menyspreable</Heatstroke.stages.0.label>
  <Heatstroke.stages.1.label>inicial</Heatstroke.stages.1.label>
  <Heatstroke.stages.2.label>menor</Heatstroke.stages.2.label>
  <Heatstroke.stages.3.label>greu</Heatstroke.stages.3.label>
  <Heatstroke.stages.4.label>extrem</Heatstroke.stages.4.label>

  <Hypothermia.label>hipotèrmia</Hypothermia.label>
  <Hypothermia.stages.0.label>menyspreable</Hypothermia.stages.0.label>
  <Hypothermia.stages.1.label>tremolors</Hypothermia.stages.1.label>
  <Hypothermia.stages.2.label>menor</Hypothermia.stages.2.label>
  <Hypothermia.stages.3.label>greu</Hypothermia.stages.3.label>
  <Hypothermia.stages.4.label>extrema</Hypothermia.stages.4.label>


</LanguageData>
