<?xml version="1.0" encoding="UTF-8"?>
<LanguageData>
  
  <!-- EN: install cochlear implant -->
  <InstallCochlearImplant.label>instal·lar un implant coclear</InstallCochlearImplant.label>
  <!-- EN: Install a cochlear implant. -->
  <InstallCochlearImplant.description>Instal·lar un implant coclear.</InstallCochlearImplant.description>
  <!-- EN: Installing cochlear implant. -->
  <InstallCochlearImplant.jobString>instal·la un implant coclear.</InstallCochlearImplant.jobString>
  
  <!-- EN: install joywire -->
  <InstallJoywire.label>instal·lar un circuit de l'alegria</InstallJoywire.label>
  <!-- EN: Install a joywire. -->
  <InstallJoywire.description>Instal·la un circuit de l'alegria.</InstallJoywire.description>
  <!-- EN: Installing joywire. -->
  <InstallJoywire.jobString>Instal·la un circuit de l'alegria.</InstallJoywire.jobString>
  
  <!-- EN: install painstopper -->
  <InstallPainstopper.label>instal·lar un circuit antidolor</InstallPainstopper.label>
  <!-- EN: Install a painstopper. -->
  <InstallPainstopper.description>Instal·la un circuit antidolor.</InstallPainstopper.description>
  <!-- EN: Installing painstopper. -->
  <InstallPainstopper.jobString>Instal·la un circuit antidolor.</InstallPainstopper.jobString>
  
  <!-- EN: install power claw -->
  <InstallPowerClaw.label>instal·lar unes urpes metàl·liques</InstallPowerClaw.label>
  <!-- EN: Install a power claw. -->
  <InstallPowerClaw.description>Instal·la unes urpes metàl·liques.</InstallPowerClaw.description>
  <!-- EN: Installing power claw. -->
  <InstallPowerClaw.jobString>Instal·la unes urpes metàl·liques.</InstallPowerClaw.jobString>
  
  <!-- EN: install prosthetic arm -->
  <InstallSimpleProstheticArm.label>instal·lar una pròtesi de braç</InstallSimpleProstheticArm.label>
  <!-- EN: Install a prosthetic arm. -->
  <InstallSimpleProstheticArm.description>Instal·lar una pròtesi de braç.</InstallSimpleProstheticArm.description>
  <!-- EN: Installing prosthetic arm. -->
  <InstallSimpleProstheticArm.jobString>Instal·la una pròtesi de braç.</InstallSimpleProstheticArm.jobString>
  
  <!-- EN: install prosthetic heart -->
  <InstallSimpleProstheticHeart.label>instal·lar una pròtesi de cor</InstallSimpleProstheticHeart.label>
  <!-- EN: Install a prosthetic heart. -->
  <InstallSimpleProstheticHeart.description>Instal·lar una pròtesi de cor</InstallSimpleProstheticHeart.description>
  <!-- EN: Installing prosthetic heart. -->
  <InstallSimpleProstheticHeart.jobString>instal·la una pròtesi de cor.</InstallSimpleProstheticHeart.jobString>
  
  <!-- EN: install prosthetic leg -->
  <InstallSimpleProstheticLeg.label>instal·lar una pròtesi de cama</InstallSimpleProstheticLeg.label>
  <!-- EN: Install a prosthetic leg. -->
  <InstallSimpleProstheticLeg.description>Instal·lar una pròtesi de cama.</InstallSimpleProstheticLeg.description>
  <!-- EN: Installing prosthetic leg. -->
  <InstallSimpleProstheticLeg.jobString>Instal·la una pròtesi de cama.</InstallSimpleProstheticLeg.jobString>
  
  <!-- EN: remove painstopper -->
  <RemovePainstopper.label>desinstal·lar un circuit antidolor</RemovePainstopper.label>
  <!-- EN: Remove the painstopper. -->
  <RemovePainstopper.description>Desinstal·lar un circuit antidolor.</RemovePainstopper.description>
  <!-- EN: Removing painstopper. -->
  <RemovePainstopper.jobString>desinstal·la un circuit antidolor.</RemovePainstopper.jobString>
  
</LanguageData>