<?xml version="1.0" encoding="UTF-8"?>
<LanguageData>
  
  <!-- EN: alpaca -->
  <Alpaca.label>alpaca</Alpaca.label>
  <Alpaca.labelFemale>femella d'alpaca</Alpaca.labelFemale>
  <Alpaca.labelFemalePlural>femelles d'alpaca</Alpaca.labelFemalePlural>
  <Alpaca.labelMale>alpaca mascle</Alpaca.labelMale>
  <Alpaca.labelMalePlural>alpaques mascles</Alpaca.labelMalePlural>
  <Alpaca.labelPlural>alpaques</Alpaca.labelPlural>
  <Alpaca.lifeStages.0.label>xai d'alpaca</Alpaca.lifeStages.0.label>
  <Alpaca.lifeStages.0.labelFemale>xai femella d'alpaca</Alpaca.lifeStages.0.labelFemale>
  <Alpaca.lifeStages.0.labelFemalePlural>xais femelles d'alpaca</Alpaca.lifeStages.0.labelFemalePlural>
  <Alpaca.lifeStages.0.labelMale>xai d'alpaca</Alpaca.lifeStages.0.labelMale>
  <Alpaca.lifeStages.0.labelMalePlural>xais d'alpaca</Alpaca.lifeStages.0.labelMalePlural>
  <Alpaca.lifeStages.0.labelPlural>xais d'alpaca</Alpaca.lifeStages.0.labelPlural>
  <Alpaca.lifeStages.1.label>alpaca</Alpaca.lifeStages.1.label>
  <Alpaca.lifeStages.1.labelFemale>femella d'alpaca</Alpaca.lifeStages.1.labelFemale>
  <Alpaca.lifeStages.1.labelFemalePlural>femelles d'alpaca</Alpaca.lifeStages.1.labelFemalePlural>
  <Alpaca.lifeStages.1.labelMale>alpaca mascle</Alpaca.lifeStages.1.labelMale>
  <Alpaca.lifeStages.1.labelMalePlural>alpaques mascles</Alpaca.lifeStages.1.labelMalePlural>
  <Alpaca.lifeStages.1.labelPlural>alpaques</Alpaca.lifeStages.1.labelPlural>
  <Alpaca.lifeStages.2.label>alpaca</Alpaca.lifeStages.2.label>
  <Alpaca.lifeStages.2.labelFemale>femella d'alpaca</Alpaca.lifeStages.2.labelFemale>
  <Alpaca.lifeStages.2.labelFemalePlural>femelles d'alpaca</Alpaca.lifeStages.2.labelFemalePlural>
  <Alpaca.lifeStages.2.labelMale>alpaca mascle</Alpaca.lifeStages.2.labelMale>
  <Alpaca.lifeStages.2.labelMalePlural>alpaques mascles</Alpaca.lifeStages.2.labelMalePlural>
  <Alpaca.lifeStages.2.labelPlural>alpaques</Alpaca.lifeStages.2.labelPlural>
  
  <!-- EN: chicken -->
  <Chicken.label>pollastre</Chicken.label>
  <!-- EN: hen -->
  <Chicken.labelFemale>gallina</Chicken.labelFemale>
  <Chicken.labelFemalePlural>gallines</Chicken.labelFemalePlural>
  <!-- EN: rooster -->
  <Chicken.labelMale>gall</Chicken.labelMale>
  <Chicken.labelMalePlural>galls</Chicken.labelMalePlural>
  <Chicken.labelPlural>pollastres</Chicken.labelPlural>
  <!-- EN: chick -->
  <Chicken.lifeStages.chick.label>pollet</Chicken.lifeStages.chick.label>
  <Chicken.lifeStages.chick.labelFemale>polleta</Chicken.lifeStages.chick.labelFemale>
  <Chicken.lifeStages.chick.labelFemalePlural>polletes</Chicken.lifeStages.chick.labelFemalePlural>
  <Chicken.lifeStages.chick.labelMale>pollet</Chicken.lifeStages.chick.labelMale>
  <Chicken.lifeStages.chick.labelMalePlural>pollets</Chicken.lifeStages.chick.labelMalePlural>
  <Chicken.lifeStages.chick.labelPlural>pollets</Chicken.lifeStages.chick.labelPlural>
  <Chicken.lifeStages.cockerel.label>pollastre</Chicken.lifeStages.cockerel.label>
  <Chicken.lifeStages.cockerel.labelFemale>gallineta</Chicken.lifeStages.cockerel.labelFemale>
  <Chicken.lifeStages.cockerel.labelFemalePlural>gallinetes</Chicken.lifeStages.cockerel.labelFemalePlural>
  <!-- EN: cockerel -->
  <Chicken.lifeStages.cockerel.labelMale>gallet</Chicken.lifeStages.cockerel.labelMale>
  <Chicken.lifeStages.cockerel.labelMalePlural>gallets</Chicken.lifeStages.cockerel.labelMalePlural>
  <Chicken.lifeStages.cockerel.labelPlural>pollastres</Chicken.lifeStages.cockerel.labelPlural>
  <Chicken.lifeStages.2.label>pollastre</Chicken.lifeStages.2.label>
  <Chicken.lifeStages.2.labelFemale>gallina</Chicken.lifeStages.2.labelFemale>
  <Chicken.lifeStages.2.labelFemalePlural>gallines</Chicken.lifeStages.2.labelFemalePlural>
  <Chicken.lifeStages.2.labelMale>gall</Chicken.lifeStages.2.labelMale>
  <Chicken.lifeStages.2.labelMalePlural>galls</Chicken.lifeStages.2.labelMalePlural>
  <Chicken.lifeStages.2.labelPlural>pollastres</Chicken.lifeStages.2.labelPlural>
  
  <!-- EN: cow -->
  <Cow.label>vaca</Cow.label>
  <!-- EN: cow -->
  <Cow.labelFemale>vaca</Cow.labelFemale>
  <Cow.labelFemalePlural>vaques</Cow.labelFemalePlural>
  <!-- EN: bull -->
  <Cow.labelMale>bou</Cow.labelMale>
  <Cow.labelMalePlural>bous</Cow.labelMalePlural>
  <Cow.labelPlural>vaques</Cow.labelPlural>
  <!-- EN: calf -->
  <Cow.lifeStages.calf.label>vedell</Cow.lifeStages.calf.label>
  <Cow.lifeStages.calf.labelFemale>vedella</Cow.lifeStages.calf.labelFemale>
  <Cow.lifeStages.calf.labelFemalePlural>vedella</Cow.lifeStages.calf.labelFemalePlural>
  <Cow.lifeStages.calf.labelMale>vedell</Cow.lifeStages.calf.labelMale>
  <Cow.lifeStages.calf.labelMalePlural>vedells</Cow.lifeStages.calf.labelMalePlural>
  <!-- EN: calves -->
  <Cow.lifeStages.calf.labelPlural>vedells</Cow.lifeStages.calf.labelPlural>
  <Cow.lifeStages.1.label>vedell</Cow.lifeStages.1.label>
  <Cow.lifeStages.1.labelFemale>vedella</Cow.lifeStages.1.labelFemale>
  <Cow.lifeStages.1.labelFemalePlural>vedelles</Cow.lifeStages.1.labelFemalePlural>
  <Cow.lifeStages.1.labelMale>vedell</Cow.lifeStages.1.labelMale>
  <Cow.lifeStages.1.labelMalePlural>vedell</Cow.lifeStages.1.labelMalePlural>
  <Cow.lifeStages.1.labelPlural>vedells</Cow.lifeStages.1.labelPlural>
  <Cow.lifeStages.2.label>vaca</Cow.lifeStages.2.label>
  <Cow.lifeStages.2.labelFemale>vaca</Cow.lifeStages.2.labelFemale>
  <Cow.lifeStages.2.labelFemalePlural>vaques</Cow.lifeStages.2.labelFemalePlural>
  <Cow.lifeStages.2.labelMale>bou</Cow.lifeStages.2.labelMale>
  <Cow.lifeStages.2.labelMalePlural>bous</Cow.lifeStages.2.labelMalePlural>
  <Cow.lifeStages.2.labelPlural>vaques</Cow.lifeStages.2.labelPlural>
  
  <!-- EN: pig -->
  <Pig.label>porc</Pig.label>
  <!-- EN: sow -->
  <Pig.labelFemale>truja</Pig.labelFemale>
  <Pig.labelFemalePlural>truges</Pig.labelFemalePlural>
  <Pig.labelMale>porc</Pig.labelMale>
  <Pig.labelMalePlural>porcs</Pig.labelMalePlural>
  <Pig.labelPlural>porcs</Pig.labelPlural>
  <!-- EN: piglet -->
  <Pig.lifeStages.piglet.label>porcell</Pig.lifeStages.piglet.label>
  <Pig.lifeStages.piglet.labelFemale>porcella</Pig.lifeStages.piglet.labelFemale>
  <Pig.lifeStages.piglet.labelFemalePlural>porcelles</Pig.lifeStages.piglet.labelFemalePlural>
  <Pig.lifeStages.piglet.labelMale>porcell</Pig.lifeStages.piglet.labelMale>
  <Pig.lifeStages.piglet.labelMalePlural>porcells</Pig.lifeStages.piglet.labelMalePlural>
  <Pig.lifeStages.piglet.labelPlural>porcells</Pig.lifeStages.piglet.labelPlural>
  <Pig.lifeStages.1.label>porc</Pig.lifeStages.1.label>
  <Pig.lifeStages.1.labelFemale>porqueta</Pig.lifeStages.1.labelFemale>
  <Pig.lifeStages.1.labelFemalePlural>porquetes</Pig.lifeStages.1.labelFemalePlural>
  <Pig.lifeStages.1.labelMale>porquet</Pig.lifeStages.1.labelMale>
  <Pig.lifeStages.1.labelMalePlural>porquets</Pig.lifeStages.1.labelMalePlural>
  <Pig.lifeStages.1.labelPlural>porcs</Pig.lifeStages.1.labelPlural>
  <Pig.lifeStages.2.label>porc</Pig.lifeStages.2.label>
  <Pig.lifeStages.2.labelFemale>truja</Pig.lifeStages.2.labelFemale>
  <Pig.lifeStages.2.labelFemalePlural>truges</Pig.lifeStages.2.labelFemalePlural>
  <Pig.lifeStages.2.labelMale>porc</Pig.lifeStages.2.labelMale>
  <Pig.lifeStages.2.labelMalePlural>porcs</Pig.lifeStages.2.labelMalePlural>
  <Pig.lifeStages.2.labelPlural>porcs</Pig.lifeStages.2.labelPlural>
  
</LanguageData>