<?xml version="1.0" encoding="utf-8"?>
<LanguageData>

  <Obedience.label>obeir</Obedience.label>
  <Obedience.description>L'animal es pot assignar a un amo a qui seguirà i defensarà.</Obedience.description>

  <Release.label>alliberar</Release.label>
  <Release.description>L'animal es pot alliberar per a atacar a objectius llunyants en comptes de només defensar a l'amo.</Release.description>

  <Rescue.label>rescatar</Rescue.label>
  <Rescue.description>L'animal rescatarà els aliats ferits i els portarà a un lloc segur.</Rescue.description>

  <Haul.label>recollir</Haul.label>
  <Haul.description>L'animal recollirà objectes de forma aleatòria de tant en tant (no es pot seleccionar els tipus d'objectes concrets).</Haul.description>


</LanguageData>
