<?xml version="1.0" encoding="UTF-8"?>
<LanguageData>
  
  <!-- EN: accepted deserter -->
  <AcceptedDeserter.label>s'ha acceptat el desertor</AcceptedDeserter.label>
  
  <!-- EN: failed to keep guests happy -->
  <FailedToKeepLodgersHappy.label>no s'ha pogut mantenir els hostes feliços</FailedToKeepLodgersHappy.label>
  
  <!-- EN: member missed shuttle -->
  <MemberMissedShuttle.label>un membre ha perdut la llançadora</MemberMissedShuttle.label>
  
  <!-- EN: monument construction expired -->
  <MonumentConstructionExpired.label>la construcció del monument ha expirat</MonumentConstructionExpired.label>
  
  <!-- EN: monument construction abandoned -->
  <MonumentConstructionMapRemoved.label>s'ha abandonat la construcció del monument</MonumentConstructionMapRemoved.label>
  
  <!-- EN: destroyed monument -->
  <MonumentDestroyed.label>s'ha destruït el monument</MonumentDestroyed.label>
  
  <!-- EN: quest completed -->
  <QuestGoodwillReward.label>s'ha completat la missió</QuestGoodwillReward.label>
  
  <!-- EN: member arrested -->
  <QuestPawnArrested.label>s'ha arrestat un membre</QuestPawnArrested.label>
  
  <!-- EN: member lost at colony -->
  <QuestPawnLost.label>s'ha perdut un membre a la colònia</QuestPawnLost.label>
  
  <!-- EN: enslaved lent prisoner -->
  <QuestPrisonerEnslaved.label>s'ha esclavitzat el presoner prestat</QuestPrisonerEnslaved.label>
  
  <!-- EN: recruited lent prisoner -->
  <QuestPrisonerRecruited.label>s'ha reclutat el presoner prestat</QuestPrisonerRecruited.label>
  
  <!-- EN: shuttle commander missed shuttle -->
  <ShuttleCommanderMissedShuttle.label>el comandant ha perdut la llançadora</ShuttleCommanderMissedShuttle.label>
  
  <!-- EN: shuttle guards missed shuttle -->
  <ShuttleGuardsMissedShuttle.label>els guardes han perdut la llançadora</ShuttleGuardsMissedShuttle.label>
  
</LanguageData>